sen2p/__init__.py
sen2p/download.py
sen2p-0.0.4.dist-info/METADATA
sen2p-0.0.4.dist-info/WHEEL
sen2p-0.0.4.dist-info/top_level.txt
sen2p-0.0.4.dist-info/RECORD
