Metadata-Version: 2.4
Name: sen2p
Version: 0.0.4
Summary: Download Sentinel-2 data from Microsoft Planetary Computer
Home-page: https://github.com/tnmthai/sen2p
Author: Thai Tran
Author-email: ThaiTran@outlook.co.nz
License: MIT
Project-URL: Homepage, https://github.com/yourusername/sen2p
Project-URL: Issues, https://github.com/yourusername/sen2p/issues
Classifier: Programming Language :: Python :: 3
Classifier: License :: OSI Approved :: MIT License
Classifier: Operating System :: OS Independent
Requires-Python: >=3.8
Requires-Dist: planetary-computer
Requires-Dist: pystac-client
Requires-Dist: rioxarray
Requires-Dist: xarray
Requires-Dist: tqdm
Requires-Dist: geopandas
Requires-Dist: shapely
Dynamic: author-email
Dynamic: home-page
Dynamic: requires-python
